jijmodeling_schema/__init__.py
jijmodeling_schema/py.typed
jijmodeling_schema/generated/__init__.py
jijmodeling_schema/generated/array_length_pb2.pyi
jijmodeling_schema/generated/binary_op_pb2.pyi
jijmodeling_schema/generated/commutative_op_pb2.pyi
jijmodeling_schema/generated/constraint_pb2.pyi
jijmodeling_schema/generated/custom_penalty_term_pb2.pyi
jijmodeling_schema/generated/decision_var_pb2.pyi
jijmodeling_schema/generated/element_pb2.pyi
jijmodeling_schema/generated/expression_pb2.pyi
jijmodeling_schema/generated/forall_pb2.pyi
jijmodeling_schema/generated/header_pb2.pyi
jijmodeling_schema/generated/jijmodeling.py
jijmodeling_schema/generated/number_lit_pb2.pyi
jijmodeling_schema/generated/placeholder_pb2.pyi
jijmodeling_schema/generated/problem_pb2.pyi
jijmodeling_schema/generated/reduction_op_pb2.pyi
jijmodeling_schema/generated/subscript_pb2.pyi
jijmodeling_schema/generated/unary_op_pb2.pyi
jijmodeling_schema-0.3.0.dist-info/LICENSE.txt
jijmodeling_schema-0.3.0.dist-info/METADATA
jijmodeling_schema-0.3.0.dist-info/WHEEL
jijmodeling_schema-0.3.0.dist-info/top_level.txt
jijmodeling_schema-0.3.0.dist-info/RECORD
